LICENCE.txt
README.md
urbandictionary_python/__init__.py
urbandictionary_python/exceptions.py
urbandictionary_python/urban_dictionary.py
urbandictionary_python.egg-info/PKG-INFO
urbandictionary_python.egg-info/SOURCES.txt
urbandictionary_python.egg-info/dependency_links.txt
urbandictionary_python.egg-info/requires.txt
urbandictionary_python.egg-info/top_level.txt
urbandictionary_python-0.0.5.dist-info/LICENCE.txt
urbandictionary_python-0.0.5.dist-info/METADATA
urbandictionary_python-0.0.5.dist-info/WHEEL
urbandictionary_python-0.0.5.dist-info/top_level.txt
urbandictionary_python-0.0.5.dist-info/RECORD
