Metadata-Version: 2.1
Name: urbandictionary-python
Version: 0.0.5
Summary: Urban Dictionary Python (Unofficial)
Home-page: UNKNOWN
Author: Abhimanyu Sharma
Author-email: speedcuberabhi@gmail.com
License: UNKNOWN
Keywords: python,urban_dictionary,requests,api
Platform: UNKNOWN
Classifier: Programming Language :: Python :: 3
Classifier: Operating System :: MacOS :: MacOS X
Classifier: Operating System :: Microsoft :: Windows
Requires-Dist: requests
